recipe_box.py
recipe_box-0.1.3.dist-info/LICENSE
recipe_box-0.1.3.dist-info/METADATA
recipe_box-0.1.3.dist-info/WHEEL
recipe_box-0.1.3.dist-info/entry_points.txt
recipe_box-0.1.3.dist-info/top_level.txt
recipe_box-0.1.3.dist-info/RECORD
