Metadata-Version: 2.1
Name: recipe-box
Version: 0.1.3
Summary: Utility to scrape recipes and put it in a local Zettelkasten.
Home-page: http://github.com/lcordier/recipe_box/
Author: Louis Cordier
Author-email: lcordier@gmail.com
License: MIT
Keywords: utility recipe scraper zettelkasten
Platform: UNKNOWN
Classifier: Development Status :: 4 - Beta
Classifier: Environment :: Console
Classifier: Intended Audience :: End Users/Desktop
Classifier: License :: OSI Approved :: MIT License
Classifier: Programming Language :: Python :: 3
Classifier: Topic :: Utilities
Requires-Dist: recipe-scrapers
